sa11y/__init__.py
sa11y/analyze.py
sa11y/scripts/axe.min.js
sa11y-0.2.3.dist-info/LICENSE.md
sa11y-0.2.3.dist-info/METADATA
sa11y-0.2.3.dist-info/WHEEL
sa11y-0.2.3.dist-info/top_level.txt
sa11y-0.2.3.dist-info/RECORD
