Metadata-Version: 2.1
Name: sa11y
Version: 0.2.3
Summary: The Selenium Accessibility Project
Home-page: https://github.com/saucelabs/sa11y
Author: titusfortner
Author-email: titusfortner@gmail.com
License: MPL-2.0
Keywords: selenium,testing,accessibility,Deque,axe
Platform: UNKNOWN
Requires-Python: >=3
License-File: LICENSE.md
Requires-Dist: selenium
Requires-Dist: pytest
